{
  "users": [
    {
      "email": "m1@instrutor.com",
      "password": "$2a$10$AuDoIQ8t7pZp0OtAhL/38OwP3lcIvSKvBgSlmDySfY3DqdCig2lfa",
      "name": "Instrutor M1",
      "module": 1,
      "isAdmin": true,
      "id": 1
    },
    {
      "email": "m2@instrutor.com",
      "password": "$2a$10$i5J/jX2kdiuRxYp8lFtELuyzHf2AvaW3bP2SUgcFOIIdTnByOY.oi",
      "name": "Instrutor M2",
      "module": 2,
      "isAdmin": true,
      "id": 2
    },
    {
      "email": "m3@instrutor.com",
      "password": "$2a$10$bUj6Se7FxJ/a/fT9cZ2I5evSTaOplA8dECpOeeOP5oEolr8g9Csdm",
      "name": "Instrutor M3",
      "module": 3,
      "isAdmin": true,
      "id": 3
    },
    {
      "email": "m4@instrutor.com",
      "password": "$2a$10$WxtFgFpAFx27mFgxphn1Z.vAxuiPxM1GzsD4XvcPTOk8H58XilzyS",
      "name": "Instrutor M4",
      "module": 4,
      "isAdmin": true,
      "id": 4
    },
    {
      "email": "m5@instrutor.com",
      "password": "$2a$10$L1bfk8hy6PXUyUaJHbY4be8/.9eevKgodwtl8MhVN5su/m/lElzKC",
      "name": "Instrutor M5",
      "module": 5,
      "isAdmin": true,
      "id": 5
    },
    {
      "email": "m6@instrutor.com",
      "password": "$2a$10$3m1D.MR2rE6C5ozEg18I8OqMXMDf6IpEpM52cBhG/6lZtGBF0DJBC",
      "name": "Instrutor M6",
      "module": 6,
      "isAdmin": true,
      "id": 6
    },
    {
      "email": "m1@aluno.com",
      "password": "$2a$10$VsrKk66vgVG1Qh/QBeRXb.6jylsjipZCrbGBQhRg8xRjI8tiZ.pDy",
      "name": "Aluno M1",
      "module": 1,
      "isAdmin": false,
      "id": 7
    },
    {
      "email": "m2@aluno.com",
      "password": "$2a$10$11NQR.FH/FccfOdSGsWtYOxUHwbXi0PwJsyhE7vRu50FqhvLbo59u",
      "name": "Aluno M2",
      "module": 2,
      "isAdmin": false,
      "id": 8
    },
    {
      "email": "m3@aluno.com",
      "password": "$2a$10$vcyNV1UuMytmqo3QeGS8d.ZsHVgYu5WX.CAJv4uuuDEyBjCpQWW/2",
      "name": "Aluno M3",
      "module": 3,
      "isAdmin": false,
      "id": 9
    },
    {
      "email": "m4@aluno.com",
      "password": "$2a$10$iT.zQquCf8OZ8cm88P38tuIbQJmoXTEseqPAhpppfaVXdTtbrV53q",
      "name": "Aluno M4",
      "module": 4,
      "isAdmin": false,
      "id": 10
    },
    {
      "email": "m5@aluno.com",
      "password": "$2a$10$0Yybwu1HHTNO2g4rHT/s8eiwD9XdViKvwf3z7s3CZH1qHHriJ3L5i",
      "name": "Aluno M5",
      "module": 5,
      "isAdmin": false,
      "id": 11
    },
    {
      "email": "m6@aluno.com",
      "password": "$2a$10$Kox2wcWGOd81dv7ewWtLrugr2fw4KPn0.I6GAO0j1rqdJizLUEVpm",
      "name": "Aluno M6",
      "module": 6,
      "isAdmin": false,
      "id": 12
    }
  ],
  "videos": [
    {
      "url": "https://demos-kenzie-academy-brasil.s3.amazonaws.com/mar22/m3/Sprint_1/GMT20220718-123537_Recording_1920x1080.mp4",
      "name": "Onboarding e Primeiros Passos no React",
      "sprintId": 1,
      "day": "Segunda-feira",
      "extra": false,
      "moduleId": 3,
      "userId": 3,
      "created_at": "18/07/22",
      "updated_at": "05/09/22",
      "marks": [
        {
          "id": 1,
          "time_video": "00:10",
          "title": "Bem-Vindo, ao React!"
        },
        {
          "id": 2,
          "time_video": "04:30",
          "title": "json-server"
        }
      ],
      "id": 1
    },
    {
      "url": "https://demos-kenzie-academy-brasil.s3.amazonaws.com/mar22/m3/Sprint_1/GMT20220719-123327_Recording_1760x900.mp4",
      "name": "Componentizando com props e children",
      "sprintId": 1,
      "day": "Terça-feira",
      "extra": false,
      "moduleId": 3,
      "userId": 3,
      "created_at": "19/07/22",
      "updated_at": "07/09/22",
      "marks": [
        {
          "id": 1,
          "time_video": "50:20",
          "title": "React"
        }
      ],
      "id": 2
    },
    {
      "url": "https://demos-kenzie-academy-brasil.s3.amazonaws.com/mar22/m3/Sprint_1/GMT20220720-123353_Recording_1760x900.mp4",
      "name": "Use State e Imutabilidade",
      "sprintId": 1,
      "day": "Quarta-feira",
      "extra": false,
      "moduleId": 3,
      "userId": 3,
      "created_at": "20/07/22",
      "updated_at": "07/09/22",
      "marks": [
        {
          "id": 1,
          "time_video": "26:10",
          "title": "Form, useState"
        }
      ],
      "id": 3
    },
    {
      "url": "https://demos-kenzie-academy-brasil.s3.amazonaws.com/mar22/m3/Sprint_1/GMT20220721-123411_Recording_1760x900.mp4",
      "name": "Conditional Render",
      "sprintId": 1,
      "day": "Quinta-feira",
      "extra": false,
      "moduleId": 3,
      "userId": 3,
      "created_at": "21/07/22",
      "updated_at": "07/09/22",
      "marks": [
        {
          "id": 1,
          "time_video": "00:16",
          "title": "Recados"
        },
        {
          "id": 2,
          "time_video": "49:50",
          "title": "slido"
        }
      ],
      "id": 4
    },
    {
      "url": "https://demos-kenzie-academy-brasil.s3.amazonaws.com/mar22/m3/Sprint_1/GMT20220722-123352_Recording_1760x900.mp4",
      "name": "Revisão Sprint 1",
      "sprintId": 1,
      "day": "Sexta-feira",
      "extra": false,
      "moduleId": 3,
      "userId": 3,
      "created_at": "22/07/22",
      "updated_at": "09/09/22",
      "marks": [
        {
          "id": 1,
          "time_video": "04:00",
          "title": "yarn create"
        },
        {
          "id": 2,
          "time_video": "43:00",
          "title": "props"
        }
      ],
      "id": 5
    },
    {
      "url": "https://demos-kenzie-academy-brasil.s3.amazonaws.com/mar22/m3/Sprint_2/video1861317007.mp4",
      "name": "Styles Modules e Styled Components",
      "sprintId": 2,
      "day": "Segunda-feira",
      "extra": false,
      "moduleId": 3,
      "userId": 3,
      "created_at": "25/07/22",
      "updated_at": "09/09/22",
      "marks": [
        {
          "id": 1,
          "time_video": "06:00",
          "title": "className: Container"
        }
      ],
      "id": 6
    },
    {
      "url": "https://demos-kenzie-academy-brasil.s3.amazonaws.com/mar22/m3/Sprint_2/GMT20220726-123330_Recording_1920x1080.mp4",
      "name": "Curso Soft Skills - Aula 1",
      "sprintId": 2,
      "day": "Terça-feira",
      "extra": false,
      "moduleId": 3,
      "userId": 3,
      "created_at": "26/07/22",
      "updated_at": "09/09/22",
      "marks": [
        {
          "id": 1,
          "time_video": "19:19",
          "title": "Gerir o tempo funciona?"
        }
      ],
      "id": 7
    },
    {
      "url": "https://demos-kenzie-academy-brasil.s3.amazonaws.com/mar22/m3/Sprint_2/GMT20220727-123123_Recording_1760x900.mp4",
      "name": "Introdução useEffect",
      "sprintId": 2,
      "day": "Quarta-feira",
      "extra": false,
      "moduleId": 3,
      "userId": 3,
      "created_at": "27/07/22",
      "updated_at": "09/09/22",
      "marks": [
        {
          "id": 1,
          "time_video": "12:15",
          "title": "useEffect"
        }
      ],
      "id": 8
    }
  ]
}
